mssev/__init__.py
mssev/armss.py
mssev/irreversible_ds.py
mssev/msss.py
mssev/pmsss.py
mssev/data/armss/manouchehrinia.tsv
mssev/data/msss/manouchehrinia.tsv
mssev/data/msss/roxburgh.tsv
mssev/data/msss/santoro.tsv
mssev/data/pmsss/narcoms.tsv
mssev-0.5.2.dist-info/LICENSE.txt
mssev-0.5.2.dist-info/METADATA
mssev-0.5.2.dist-info/WHEEL
mssev-0.5.2.dist-info/top_level.txt
mssev-0.5.2.dist-info/RECORD
