Metadata-Version: 2.1
Name: mssev
Version: 0.5.2
Summary: This library contains several utilities and scores commonly used in multiple
Author-email: Alejandro Caravaca Puchades <acaravacapuchades@icloud.com>
License: GPL-3.0-or-later
Classifier: Programming Language :: Python :: 3
Classifier: Operating System :: OS Independent
Classifier: License :: OSI Approved :: GNU General Public License v3 or later (GPLv3+)
Classifier: Intended Audience :: Healthcare Industry
Classifier: Intended Audience :: Science/Research
Classifier: Topic :: Scientific/Engineering :: Bio-Informatics
Classifier: Topic :: Scientific/Engineering :: Information Analysis
Classifier: Topic :: Scientific/Engineering :: Medical Science Apps.
License-File: LICENSE.txt
Requires-Dist: numpy (==1.23.2)
Requires-Dist: pandas (==1.4.3)
Requires-Dist: python-dateutil (==2.8.2)
Requires-Dist: pytz (==2022.2.1)
Requires-Dist: six (==1.16.0)
